LICENSE
regta_period/__init__.py
regta_period/enums.py
regta_period/periods.py
regta_period-0.2.0.dist-info/LICENSE
regta_period-0.2.0.dist-info/WHEEL
regta_period-0.2.0.dist-info/METADATA
regta_period-0.2.0.dist-info/RECORD
