Metadata-Version: 2.1
Name: regta-period
Version: 0.2.0
Summary: Moment-independent periods
Home-page: https://regta-period.alinsky.tech
License: MIT
Keywords: time,intervals,periods,regta
Author: Vladimir Alinsky
Author-email: Vladimir@Alinsky.tech
Requires-Python: >=3.7.2,<4.0
Classifier: Development Status :: 5 - Production/Stable
Classifier: License :: OSI Approved :: MIT License
Classifier: Programming Language :: Python :: 3
Classifier: Programming Language :: Python :: 3.10
Classifier: Programming Language :: Python :: 3.11
Classifier: Programming Language :: Python :: 3.7
Classifier: Programming Language :: Python :: 3.8
Classifier: Programming Language :: Python :: 3.9
Project-URL: Repository, https://github.com/SKY-ALIN/regta-period
